{
  "username": "Empy-ai09",
  "totalStars": 2,
  "totalCommits": 162,
  "publicRepos": 7,
  "languages": {
    "JavaScript": 25539,
    "CSS": 17935,
    "HTML": 15430,
    "message": "0API rate limit exceeded for 20.55.223.212. (But here's the good news: Authenticated requests get a higher rate limit. Check out the documentation for more details.)",
    "documentation_url": "0https://docs.github.com/rest/overview/resources-in-the-rest-api#rate-limiting"
  },
  "updated": "2025-07-22T02:01:53.489Z"
}